{
  "site": "ENISA",
  "crawled_at": "2026-07-24 22:06:27",
  "total_found": 15,
  "saved": 14,
  "articles": [
    {
      "title": "Incident management",
      "url": "https://www.enisa.europa.eu/topics/incident-management"
    },
    {
      "title": "Skills and competences (for companies)",
      "url": "https://www.enisa.europa.eu/topics/skills-and-competences-for-companies"
    },
    {
      "title": "Cyber Hygiene",
      "url": "https://www.enisa.europa.eu/topics/cyber-hygiene"
    },
    {
      "title": "Cyber Incident Awareness",
      "url": "https://www.enisa.europa.eu/topics/cyber-incident-awareness"
    },
    {
      "title": "Education and career path",
      "url": "https://www.enisa.europa.eu/topics/education-and-career-path"
    },
    {
      "title": "Publications",
      "url": "https://www.enisa.europa.eu/publications"
    },
    {
      "title": "Press office",
      "url": "https://www.enisa.europa.eu/press-office"
    },
    {
      "title": "Corporate identity",
      "url": "https://www.enisa.europa.eu/press-office/corporate-identity"
    },
    {
      "title": "Cybersecurity material",
      "url": "https://www.enisa.europa.eu/press-office/cybersecurity-material"
    },
    {
      "title": "How we work",
      "url": "https://www.enisa.europa.eu/about-enisa/How-we-work"
    },
    {
      "title": "Accounting and Finance",
      "url": "https://www.enisa.europa.eu/about-enisa/accounting-finance/accounting-finance"
    },
    {
      "title": "Policies and Procedures",
      "url": "https://www.enisa.europa.eu/about-enisa/procedures-and-policies"
    },
    {
      "title": "Data Protection",
      "url": "https://www.enisa.europa.eu/about-enisa/data-protection/data-protection"
    },
    {
      "title": "Transparency",
      "url": "https://www.enisa.europa.eu/about-enisa/transparency"
    }
  ]
}